COPYING.LAME
LICENSE
fast_mp3_augment-0.2.0.dist-info/METADATA
fast_mp3_augment-0.2.0.dist-info/WHEEL
fast_mp3_augment-0.2.0.dist-info/licenses/COPYING.LAME
fast_mp3_augment-0.2.0.dist-info/licenses/LICENSE
fast_mp3_augment/__init__.py
fast_mp3_augment/_mp3augment.abi3.so
fast_mp3_augment-0.2.0.dist-info/RECORD
