Metadata-Version: 2.4
Name: fast_mp3_augment
Version: 0.2.0
Classifier: Programming Language :: Rust
Classifier: Programming Language :: Python :: 3 :: Only
Classifier: Topic :: Multimedia :: Sound/Audio :: Conversion
Requires-Dist: numpy>=1.22,<3
Requires-Dist: numpy-minmax
License-File: LICENSE
License-File: COPYING.LAME
Summary: Fast in‑memory MP3 encode‑decode augmentation for audiomentations
Author-email: Iver Jordal <iver56@hotmail.com>
License: LGPL-2.1-or-later
Requires-Python: >=3.10
Project-URL: Homepage, https://github.com/iver56/fast-mp3-augment
